ort_nightly_directml-1.11.0.dev20220320001.data/purelib/onnxruntime/LICENSE
ort_nightly_directml-1.11.0.dev20220320001.data/purelib/onnxruntime/Privacy.md
ort_nightly_directml-1.11.0.dev20220320001.data/purelib/onnxruntime/ThirdPartyNotices.txt
ort_nightly_directml-1.11.0.dev20220320001.data/purelib/onnxruntime/__init__.py
ort_nightly_directml-1.11.0.dev20220320001.data/purelib/onnxruntime/backend/__init__.py
ort_nightly_directml-1.11.0.dev20220320001.data/purelib/onnxruntime/backend/backend.py
ort_nightly_directml-1.11.0.dev20220320001.data/purelib/onnxruntime/backend/backend_rep.py
ort_nightly_directml-1.11.0.dev20220320001.data/purelib/onnxruntime/capi/DirectML.dll
ort_nightly_directml-1.11.0.dev20220320001.data/purelib/onnxruntime/capi/__init__.py
ort_nightly_directml-1.11.0.dev20220320001.data/purelib/onnxruntime/capi/_ld_preload.py
ort_nightly_directml-1.11.0.dev20220320001.data/purelib/onnxruntime/capi/_pybind_state.py
ort_nightly_directml-1.11.0.dev20220320001.data/purelib/onnxruntime/capi/onnxruntime_collect_build_info.py
ort_nightly_directml-1.11.0.dev20220320001.data/purelib/onnxruntime/capi/onnxruntime_inference_collection.py
ort_nightly_directml-1.11.0.dev20220320001.data/purelib/onnxruntime/capi/onnxruntime_providers_shared.dll
ort_nightly_directml-1.11.0.dev20220320001.data/purelib/onnxruntime/capi/onnxruntime_pybind11_state.pyd
ort_nightly_directml-1.11.0.dev20220320001.data/purelib/onnxruntime/capi/onnxruntime_validation.py
ort_nightly_directml-1.11.0.dev20220320001.data/purelib/onnxruntime/capi/version_info.py
ort_nightly_directml-1.11.0.dev20220320001.data/purelib/onnxruntime/capi/training/__init__.py
ort_nightly_directml-1.11.0.dev20220320001.data/purelib/onnxruntime/datasets/__init__.py
ort_nightly_directml-1.11.0.dev20220320001.data/purelib/onnxruntime/datasets/logreg_iris.onnx
ort_nightly_directml-1.11.0.dev20220320001.data/purelib/onnxruntime/datasets/mul_1.onnx
ort_nightly_directml-1.11.0.dev20220320001.dist-info/METADATA
ort_nightly_directml-1.11.0.dev20220320001.dist-info/WHEEL
ort_nightly_directml-1.11.0.dev20220320001.dist-info/entry_points.txt
ort_nightly_directml-1.11.0.dev20220320001.dist-info/top_level.txt
ort_nightly_directml-1.11.0.dev20220320001.dist-info/RECORD
